[
  {
    "type": "structural",
    "description": "Added new standings fields for season 12",
    "endpoint": "standings",
    "merge": {
      "gamesPlayed": {},
      "runs": {}
    }
  },
  {
    "type": "structural",
    "description": "Team fields for eDensity, stadiums, evolution, and others for season 12",
    "endpoint": "team",
    "merge": {
      "eDensity": 0,
      "imPostion": 0,
      "evolution": 0,
      "stadium": null,
      "eVelocity": 0,
      "winStreak": 0,
      "state": {}
    }
  }

]